.hgignore
CHANGES.txt
LICENSE.txt
README.txt
bootstrap.py
buildout.cfg
setup.py
js/__init__.py
js.jquery_ba_resize.egg-info/PKG-INFO
js.jquery_ba_resize.egg-info/SOURCES.txt
js.jquery_ba_resize.egg-info/dependency_links.txt
js.jquery_ba_resize.egg-info/entry_points.txt
js.jquery_ba_resize.egg-info/namespace_packages.txt
js.jquery_ba_resize.egg-info/not-zip-safe
js.jquery_ba_resize.egg-info/requires.txt
js.jquery_ba_resize.egg-info/top_level.txt
js/jquery_ba_resize/__init__.py
js/jquery_ba_resize/test_jquery.ba-resize.txt
js/jquery_ba_resize/resources/README.txt
js/jquery_ba_resize/resources/jquery.ba-resize.js
js/jquery_ba_resize/resources/jquery.ba-resize.min.js