Metadata-Version: 1.0
Name: js.jquery-ba-resize
Version: 1.1
Summary: Fanstatic packaging of jquery.ba-resize
Home-page: UNKNOWN
Author: Fanstatic Developers
Author-email: fanstatic@googlegroups.com
License: BSD
Platform: UNKNOWN
